{
	"info": {
		"_postman_id": "6f0ca46b-9b6a-49b5-9da6-787bd827e2d5",
		"name": "TrickingAPI Docs",
		"description": "Consumption-only API for barebones Tricking Terminology Data\n\nContact Support:\n Email: admin@trickingapi.dev",
		"schema": "https://schema.getpostman.com/json/collection/v2.1.0/collection.json",
		"_uid": "25462308-6f0ca46b-9b6a-49b5-9da6-787bd827e2d5"
	},
	"item": [
		{
			"name": "tricks",
			"item": [
				{
					"name": "Get All Tricks from TrickingApi/data/tricks",
					"id": "368ad6da-1f7b-48b4-bb71-f6fac33c1117",
					"protocolProfileBehavior": {
						"disableBodyPruning": true
					},
					"request": {
						"method": "GET",
						"header": [
							{
								"key": "Accept",
								"value": "application/json"
							}
						],
						"url": {
							"raw": "{{baseUrl}}/tricks",
							"host": [
								"{{baseUrl}}"
							],
							"path": [
								"tricks"
							]
						}
					},
					"response": [
						{
							"id": "3a95bc99-ccce-4f09-a8db-060785c31a86",
							"name": "OK",
							"originalRequest": {
								"method": "GET",
								"header": [],
								"url": {
									"raw": "{{baseUrl}}/tricks",
									"host": [
										"{{baseUrl}}"
									],
									"path": [
										"tricks"
									]
								}
							},
							"status": "OK",
							"code": 200,
							"_postman_previewlanguage": "json",
							"header": [
								{
									"key": "Content-Type",
									"value": "application/json"
								}
							],
							"cookie": [],
							"body": "{\n  \"value\": \"reference #components/schemas/Trick not found in the OpenAPI spec\"\n}"
						},
						{
							"id": "2c9f1085-8072-4851-97b7-ba0ce2ba4681",
							"name": "Unexpected error",
							"originalRequest": {
								"method": "GET",
								"header": [],
								"url": {
									"raw": "{{baseUrl}}/tricks",
									"host": [
										"{{baseUrl}}"
									],
									"path": [
										"tricks"
									]
								}
							},
							"status": "Internal Server Error",
							"code": 500,
							"_postman_previewlanguage": "json",
							"header": [
								{
									"key": "Content-Type",
									"value": "application/json"
								}
							],
							"cookie": [],
							"body": "{\n  \"message\": \"<string>\",\n  \"data\": \"<string>\",\n  \"success\": \"<boolean>\"\n}"
						}
					]
				},
				{
					"name": "Get Trick by TrickId",
					"id": "d7f9e7d3-57ac-41ad-9dbe-7e54593b0e16",
					"protocolProfileBehavior": {
						"disableBodyPruning": true
					},
					"request": {
						"method": "GET",
						"header": [
							{
								"key": "Accept",
								"value": "application/json"
							}
						],
						"url": {
							"raw": "{{baseUrl}}/tricks/:TrickId",
							"host": [
								"{{baseUrl}}"
							],
							"path": [
								"tricks",
								":TrickId"
							],
							"variable": [
								{
									"key": "TrickId",
									"value": "<string>",
									"description": "(Required) The unique identifier of the trick"
								}
							]
						}
					},
					"response": [
						{
							"id": "68617ab9-b82f-4dcf-9cde-0f158529105a",
							"name": "The trick corresponding to the provided `TrickId`",
							"originalRequest": {
								"method": "GET",
								"header": [],
								"url": {
									"raw": "{{baseUrl}}/tricks/:TrickId",
									"host": [
										"{{baseUrl}}"
									],
									"path": [
										"tricks",
										":TrickId"
									],
									"variable": [
										{
											"key": "TrickId",
											"value": "<string>",
											"description": "(Required) The unique identifier of the trick"
										}
									]
								}
							},
							"status": "OK",
							"code": 200,
							"_postman_previewlanguage": "json",
							"header": [
								{
									"key": "Content-Type",
									"value": "application/json"
								}
							],
							"cookie": [],
							"body": "{\n  \"id\": \"<string>\",\n  \"name\": \"<string>\",\n  \"aliases\": [\n    \"<string>\",\n    \"<string>\"\n  ],\n  \"categories\": [\n    {\n      \"value\": \"reference #components/schemas/TrickCategory not found in the OpenAPI spec\"\n    },\n    {\n      \"value\": \"reference #components/schemas/TrickCategory not found in the OpenAPI spec\"\n    }\n  ],\n  \"prerequisites\": [\n    \"<string>\",\n    \"<string>\"\n  ],\n  \"nextTricks\": [\n    \"<string>\",\n    \"<string>\"\n  ],\n  \"description\": \"<string>\"\n}"
						},
						{
							"id": "9c2ca0c6-189a-41d9-aa33-65784af1b7af",
							"name": "No Trick found for the provided `TrickId`",
							"originalRequest": {
								"method": "GET",
								"header": [],
								"url": {
									"raw": "{{baseUrl}}/tricks/:TrickId",
									"host": [
										"{{baseUrl}}"
									],
									"path": [
										"tricks",
										":TrickId"
									],
									"variable": [
										{
											"key": "TrickId",
											"value": "<string>",
											"description": "(Required) The unique identifier of the trick"
										}
									]
								}
							},
							"status": "Not Found",
							"code": 404,
							"_postman_previewlanguage": "json",
							"header": [
								{
									"key": "Content-Type",
									"value": "application/json"
								}
							],
							"cookie": [],
							"body": "{\n  \"message\": \"<string>\",\n  \"data\": \"<string>\",\n  \"success\": \"<boolean>\"\n}"
						},
						{
							"id": "f828d92c-b819-4a54-bf43-2281995c4971",
							"name": "Unexpected error",
							"originalRequest": {
								"method": "GET",
								"header": [],
								"url": {
									"raw": "{{baseUrl}}/tricks/:TrickId",
									"host": [
										"{{baseUrl}}"
									],
									"path": [
										"tricks",
										":TrickId"
									],
									"variable": [
										{
											"key": "TrickId",
											"value": "<string>",
											"description": "(Required) The unique identifier of the trick"
										}
									]
								}
							},
							"status": "Internal Server Error",
							"code": 500,
							"_postman_previewlanguage": "json",
							"header": [
								{
									"key": "Content-Type",
									"value": "application/json"
								}
							],
							"cookie": [],
							"body": "{\n  \"message\": \"<string>\",\n  \"data\": \"<string>\",\n  \"success\": \"<boolean>\"\n}"
						}
					]
				},
				{
					"name": "Get All Trick Names and their ids from TrickingApi/data/tricks",
					"id": "c1fe91cc-c34e-4392-9a0c-a8fc9c740133",
					"protocolProfileBehavior": {
						"disableBodyPruning": true
					},
					"request": {
						"method": "GET",
						"header": [
							{
								"key": "Accept",
								"value": "application/json"
							}
						],
						"url": {
							"raw": "{{baseUrl}}/tricks/names",
							"host": [
								"{{baseUrl}}"
							],
							"path": [
								"tricks",
								"names"
							]
						}
					},
					"response": [
						{
							"id": "09b56115-7e4d-4326-8b61-2554343fdea1",
							"name": "OK",
							"originalRequest": {
								"method": "GET",
								"header": [],
								"url": {
									"raw": "{{baseUrl}}/tricks/names",
									"host": [
										"{{baseUrl}}"
									],
									"path": [
										"tricks",
										"names"
									]
								}
							},
							"status": "OK",
							"code": 200,
							"_postman_previewlanguage": "json",
							"header": [
								{
									"key": "Content-Type",
									"value": "application/json"
								}
							],
							"cookie": [],
							"body": "{\n  \"sit37\": \"<string>\"\n}"
						},
						{
							"id": "ba0de9e7-2993-42c8-a2a2-c0b771917e34",
							"name": "Unexpected error",
							"originalRequest": {
								"method": "GET",
								"header": [],
								"url": {
									"raw": "{{baseUrl}}/tricks/names",
									"host": [
										"{{baseUrl}}"
									],
									"path": [
										"tricks",
										"names"
									]
								}
							},
							"status": "Internal Server Error",
							"code": 500,
							"_postman_previewlanguage": "json",
							"header": [
								{
									"key": "Content-Type",
									"value": "application/json"
								}
							],
							"cookie": [],
							"body": "{\n  \"message\": \"<string>\",\n  \"data\": \"<string>\",\n  \"success\": \"<boolean>\"\n}"
						}
					]
				}
			],
			"id": "497551e0-f841-4e0c-ab37-8e736a7ca3df"
		},
		{
			"name": "categories",
			"item": [
				{
					"name": "Get All Existing Trick Category Names from TrickingAPI/data/tricks",
					"id": "7e68303b-01b0-442f-94db-95238848271a",
					"protocolProfileBehavior": {
						"disableBodyPruning": true
					},
					"request": {
						"method": "GET",
						"header": [
							{
								"key": "Accept",
								"value": "application/json"
							}
						],
						"url": {
							"raw": "{{baseUrl}}/categories",
							"host": [
								"{{baseUrl}}"
							],
							"path": [
								"categories"
							]
						},
						"description": "Reads and returns all existing categories of tricks from the tricks.json file at https://github.com/TrickingApi/trickingapi"
					},
					"response": [
						{
							"id": "c7342eb0-5166-4149-a239-5640f67d5fde",
							"name": "OK",
							"originalRequest": {
								"method": "GET",
								"header": [],
								"url": {
									"raw": "{{baseUrl}}/categories",
									"host": [
										"{{baseUrl}}"
									],
									"path": [
										"categories"
									]
								}
							},
							"status": "OK",
							"code": 200,
							"_postman_previewlanguage": "json",
							"header": [
								{
									"key": "Content-Type",
									"value": "application/json"
								}
							],
							"cookie": [],
							"body": "[\n  \"<string>\",\n  \"<string>\"\n]"
						},
						{
							"id": "3941b95d-2601-4dfe-b4e4-5832178233fc",
							"name": "Unexpected error",
							"originalRequest": {
								"method": "GET",
								"header": [],
								"url": {
									"raw": "{{baseUrl}}/categories",
									"host": [
										"{{baseUrl}}"
									],
									"path": [
										"categories"
									]
								}
							},
							"status": "Internal Server Error",
							"code": 500,
							"_postman_previewlanguage": "json",
							"header": [
								{
									"key": "Content-Type",
									"value": "application/json"
								}
							],
							"cookie": [],
							"body": "{\n  \"message\": \"<string>\",\n  \"data\": \"<string>\",\n  \"success\": \"<boolean>\"\n}"
						}
					]
				},
				{
					"name": "Get All Tricks Grouped by Categories from TrickingApi/data/tricks",
					"id": "c2f7da22-489a-4629-a917-a0d256b02b38",
					"protocolProfileBehavior": {
						"disableBodyPruning": true
					},
					"request": {
						"method": "GET",
						"header": [
							{
								"key": "Accept",
								"value": "application/json"
							}
						],
						"url": {
							"raw": "{{baseUrl}}/categories/tricks",
							"host": [
								"{{baseUrl}}"
							],
							"path": [
								"categories",
								"tricks"
							]
						},
						"description": "Reads and returns a mapping of categories to list of tricks from the tricks.json file at https://github.com/TrickingApi/trickingapi"
					},
					"response": [
						{
							"id": "32e09992-e7ce-4105-bebb-d9defab907e0",
							"name": "OK",
							"originalRequest": {
								"method": "GET",
								"header": [],
								"url": {
									"raw": "{{baseUrl}}/categories/tricks",
									"host": [
										"{{baseUrl}}"
									],
									"path": [
										"categories",
										"tricks"
									]
								}
							},
							"status": "OK",
							"code": 200,
							"_postman_previewlanguage": "json",
							"header": [
								{
									"key": "Content-Type",
									"value": "application/json"
								}
							],
							"cookie": [],
							"body": "{\n  \"ex_c\": [\n    {\n      \"id\": \"<string>\",\n      \"name\": \"<string>\",\n      \"aliases\": [\n        \"<string>\",\n        \"<string>\"\n      ],\n      \"categories\": [\n        {\n          \"value\": \"reference #components/schemas/TrickCategory not found in the OpenAPI spec\"\n        },\n        {\n          \"value\": \"reference #components/schemas/TrickCategory not found in the OpenAPI spec\"\n        }\n      ],\n      \"prerequisites\": [\n        \"<string>\",\n        \"<string>\"\n      ],\n      \"nextTricks\": [\n        \"<string>\",\n        \"<string>\"\n      ],\n      \"description\": \"<string>\"\n    },\n    {\n      \"id\": \"<string>\",\n      \"name\": \"<string>\",\n      \"aliases\": [\n        \"<string>\",\n        \"<string>\"\n      ],\n      \"categories\": [\n        {\n          \"value\": \"reference #components/schemas/TrickCategory not found in the OpenAPI spec\"\n        },\n        {\n          \"value\": \"reference #components/schemas/TrickCategory not found in the OpenAPI spec\"\n        }\n      ],\n      \"prerequisites\": [\n        \"<string>\",\n        \"<string>\"\n      ],\n      \"nextTricks\": [\n        \"<string>\",\n        \"<string>\"\n      ],\n      \"description\": \"<string>\"\n    }\n  ]\n}"
						},
						{
							"id": "71cbc74a-a594-423c-b181-8aa12dd95c9c",
							"name": "Unexpected error",
							"originalRequest": {
								"method": "GET",
								"header": [],
								"url": {
									"raw": "{{baseUrl}}/categories/tricks",
									"host": [
										"{{baseUrl}}"
									],
									"path": [
										"categories",
										"tricks"
									]
								}
							},
							"status": "Internal Server Error",
							"code": 500,
							"_postman_previewlanguage": "json",
							"header": [
								{
									"key": "Content-Type",
									"value": "application/json"
								}
							],
							"cookie": [],
							"body": "{\n  \"message\": \"<string>\",\n  \"data\": \"<string>\",\n  \"success\": \"<boolean>\"\n}"
						}
					]
				},
				{
					"name": "Get All Tricks Grouped Under A Category from TrickingApi/data/tricks",
					"id": "b77d6ba7-d829-466a-bd46-93d2fa93d98c",
					"protocolProfileBehavior": {
						"disableBodyPruning": true
					},
					"request": {
						"method": "GET",
						"header": [
							{
								"key": "Accept",
								"value": "application/json"
							}
						],
						"url": {
							"raw": "{{baseUrl}}/categories/:CategoryName",
							"host": [
								"{{baseUrl}}"
							],
							"path": [
								"categories",
								":CategoryName"
							],
							"variable": [
								{
									"key": "CategoryName",
									"value": "<string>",
									"description": "(Required) The unique identifier of the TrickCategory"
								}
							]
						},
						"description": "Reads and returns a list of tricks for a specific category from the tricks.json file at https://github.com/TrickingApi/trickingapi"
					},
					"response": [
						{
							"id": "2adc191c-68f2-4487-8199-568bf91b2f10",
							"name": "OK",
							"originalRequest": {
								"method": "GET",
								"header": [],
								"url": {
									"raw": "{{baseUrl}}/categories/:CategoryName",
									"host": [
										"{{baseUrl}}"
									],
									"path": [
										"categories",
										":CategoryName"
									],
									"variable": [
										{
											"key": "CategoryName",
											"value": "<string>",
											"description": "(Required) The unique identifier of the TrickCategory"
										}
									]
								}
							},
							"status": "OK",
							"code": 200,
							"_postman_previewlanguage": "json",
							"header": [
								{
									"key": "Content-Type",
									"value": "application/json"
								}
							],
							"cookie": [],
							"body": "[\n  {\n    \"id\": \"<string>\",\n    \"name\": \"<string>\",\n    \"aliases\": [\n      \"<string>\",\n      \"<string>\"\n    ],\n    \"categories\": [\n      {\n        \"value\": \"reference #components/schemas/TrickCategory not found in the OpenAPI spec\"\n      },\n      {\n        \"value\": \"reference #components/schemas/TrickCategory not found in the OpenAPI spec\"\n      }\n    ],\n    \"prerequisites\": [\n      \"<string>\",\n      \"<string>\"\n    ],\n    \"nextTricks\": [\n      \"<string>\",\n      \"<string>\"\n    ],\n    \"description\": \"<string>\"\n  },\n  {\n    \"id\": \"<string>\",\n    \"name\": \"<string>\",\n    \"aliases\": [\n      \"<string>\",\n      \"<string>\"\n    ],\n    \"categories\": [\n      {\n        \"value\": \"reference #components/schemas/TrickCategory not found in the OpenAPI spec\"\n      },\n      {\n        \"value\": \"reference #components/schemas/TrickCategory not found in the OpenAPI spec\"\n      }\n    ],\n    \"prerequisites\": [\n      \"<string>\",\n      \"<string>\"\n    ],\n    \"nextTricks\": [\n      \"<string>\",\n      \"<string>\"\n    ],\n    \"description\": \"<string>\"\n  }\n]"
						}
					]
				}
			],
			"id": "383c0e42-b83e-4601-9332-86e3e8649ed7"
		}
	],
	"variable": [
		{
			"id": "00a17ad7-29e5-4010-aac4-658e47fadfdf",
			"key": "baseUrl",
			"value": "https://trickingapi.dev/api",
			"type": "string"
		}
	]
}